s3_log_query/S3LogQuery.py
s3_log_query/__init__.py
tests/__init__.py
tests/test_s3_log_query.py
s3_log_query-1.0.0.dist-info/AUTHORS.rst
s3_log_query-1.0.0.dist-info/LICENSE.txt
s3_log_query-1.0.0.dist-info/METADATA
s3_log_query-1.0.0.dist-info/WHEEL
s3_log_query-1.0.0.dist-info/top_level.txt
s3_log_query-1.0.0.dist-info/RECORD
