Metadata-Version: 2.1
Name: s3-log-query
Version: 1.0.0
Summary: Query S3 Log Files
Home-page: https://github.com/mikethoun/s3-log-query
Author: Mike Thoun
Author-email: mikethoun@gmail.com
License: Apache License 2.0
Platform: UNKNOWN
Classifier: Programming Language :: Python :: 3
Classifier: License :: OSI Approved :: Apache Software License
Requires-Dist: boto3 (~=1.17.12)
Requires-Dist: python-dateutil (~=2.8.1)
Requires-Dist: setuptools (~=53.0.0)
Requires-Dist: pandas (~=1.2.2)
